odoo9_addon_web_responsive-9.0.3.0.0-py2.7-nspkg.pth
odoo9_addon_web_responsive-9.0.3.0.0.dist-info/DESCRIPTION.rst
odoo9_addon_web_responsive-9.0.3.0.0.dist-info/METADATA
odoo9_addon_web_responsive-9.0.3.0.0.dist-info/RECORD
odoo9_addon_web_responsive-9.0.3.0.0.dist-info/WHEEL
odoo9_addon_web_responsive-9.0.3.0.0.dist-info/metadata.json
odoo9_addon_web_responsive-9.0.3.0.0.dist-info/namespace_packages.txt
odoo9_addon_web_responsive-9.0.3.0.0.dist-info/top_level.txt
odoo_addons/web_responsive/README.rst
odoo_addons/web_responsive/__init__.py
odoo_addons/web_responsive/__openerp__.py
odoo_addons/web_responsive/i18n/es.po
odoo_addons/web_responsive/static/description/icon.png
odoo_addons/web_responsive/static/lib/css/drawer.3.2.2.css
odoo_addons/web_responsive/static/lib/js/bililiteRange.2.6.js
odoo_addons/web_responsive/static/lib/js/drawer.3.2.2.js
odoo_addons/web_responsive/static/lib/js/iscroll-probe.5.2.0.js
odoo_addons/web_responsive/static/lib/js/jquery.sendkeys.4.js
odoo_addons/web_responsive/static/src/js/web_responsive.js
odoo_addons/web_responsive/static/src/less/app_drawer.less
odoo_addons/web_responsive/static/src/less/form_view.less
odoo_addons/web_responsive/static/src/less/main.less
odoo_addons/web_responsive/static/src/less/navbar.less
odoo_addons/web_responsive/static/src/less/variables.less
odoo_addons/web_responsive/static/src/xml/app_drawer_menu_search.xml
odoo_addons/web_responsive/static/tests/js/web_responsive.js
odoo_addons/web_responsive/tests/test_ui.py
odoo_addons/web_responsive/views/assets.xml
odoo_addons/web_responsive/views/web.xml
