Metadata-Version: 2.0
Name: odoo9-addon-web-responsive
Version: 9.0.3.0.0
Summary: It provides a mobile compliant interface for Odoo Community web
Home-page: https://laslabs.com/
Author: LasLabs, Tecnativa, Odoo Community Association (OCA)
Author-email: support@odoo-community.org
License: LGPL-3
Platform: UNKNOWN
Classifier: Programming Language :: Python
Classifier: Framework :: Odoo
Classifier: License :: OSI Approved :: GNU Lesser General Public License v3 (LGPLv3)
Requires-Python: ~=2.7
Requires-Dist: odoo (<9.1a,>=9.0a)
